player2py/__init__.py
player2py/client.py
player2py/exceptions.py
player2py/models.py
player2py-0.1.1.dist-info/licenses/LICENSE
player2py-0.1.1.dist-info/METADATA
player2py-0.1.1.dist-info/WHEEL
player2py-0.1.1.dist-info/top_level.txt
player2py-0.1.1.dist-info/RECORD
